{
  "id": "uspto-19044532",
  "title": "APPARATUS AND METHOD FOR PERSONALIZATION OF EDUCATIONAL MACHINE LEARNING MODELS",
  "inventors": [
    "Michael Everest"
  ],
  "technology_class": "G06F",
  "summary": "Abstract of the Disclosure:\nAn apparatus and method for personalization of educational machine learning models. The apparatus includes at least a processor and a memory communicatively connected to the at least a processor. The memory instructs the processor to receive input data comprising one or more of a user profile and a request datum, generate, using a return generator, return output based on the request datum, identify, using a machine learning model, attribute data of the input data, generate, using a classifier, one or more classifications for the input data as a function of the attribute data associated with the input data, modify, using a natural language processor, the return output as a function of the user profile and one or more classifications assigned to the input data to generate user specific output, and display, using a downstream device, the user specific output.\n1 Attorney Docket No. 1450-0\n12USU1\n\n\n\n \n ABST\n\n 19044532\n\n 1\n\n Abstract of the Disclosure:\n\n An apparatus and method for personalization of educational machine learning models. The apparatus includes at least a processor and a memory communicatively connected to the at least a processor. The memory instructs the processor to receive input data comprising one or more of a user profile and a request datum, generate, using a return generator, return output based on the request datum, identify, using a machine learning model, attribute data of the input data, generate, using a classifier, one or more classifications for the input data as a function of the attribute data associated with the input data, modify, using a natural language processor, the return output as a function of the user profile and one or more classifications assigned to the input data to generate user specific output, and display, using a downstream device, the user specific output.",
  "details": "LISTING OF CLAIMS\nThis listing of claims will replace all prior versions, and listings, of claims in the application:\n1\n1. (Currently Amended) An apparatus for personalization of educational machine learning models, wherein the apparatus comprises:at least a computing device, wherein the computing device comprises:\na memory; and\nat least a processor communicatively connected to the memory, wherein the memory contains instructions configuring the at least a processor to:\nreceive input data comprising one or more of a user profile and a request datum;\ngenerate, using a return generator, return output based on the request datum;\nidentify, using a machine learning model, attribute data of the input data;\ngenerate, using a classifier, one or more classifications for the input data as a function of the attribute data associated with the input data, wherein g\nenerating\n the one of more classification using the classifier comprises:comparing, using an evaluation model, historical classifications to future activity;\n\ndetermining, using a comparison of the historical classifications to the future activity, targ\net classifications;\n\ng\nenerating\n a classification score as a function of a difference between the historical classifications and the targ\net classifications;\n and iteratively training the classifier using\n the classification score;\n\nmodify, using a natural language processor, the return output as a function of the user profile and one or more classifications assigned to the input data to generate user specific output;\ndisplay, using a downstream device, the user specific output.\nCurrently amended\n\n2\n2. (Original) The apparatus of claim 1, \nfurther configured to generate, using the machine learning model, an alternative user specific output as a function of the input data, wherein the input data comprises activity data.\nOriginal\n\n3\n3. (Canceled)\n\nCanceled\n\n4\n4. (Currently Amended) The apparatus of claim [[3]] 1,\n wherein the at least a processor is further configured to:compare, using the evaluation model, a historical user specific output with the future activity;\ndetermine, using a comparison of the historical user specific output with the future activity, a target user specific output;\ngenerate a user specific output score as a function of a difference between the historical user specific output and the future activity; and\niteratively train the natural language processor using the user specific output score.\n\nCurrently amended\n\n5\n5. (Original) The apparatus of claim 4, \nwherein the evaluation model is further configured to:calculate a composite score as a function of integrating the classification score, the user specific output score;\niteratively update the composite score based on user feedback received though an interactive element; and\nprovide the composite score as training feedback for the classifier and the natural language processor.\n\nOriginal\n\n6\n6. (Original) The apparatus of claim 1, \nfurther comprising a database communicatively connected to the at least a processor, wherein the at least a processor is configured to store, using the database, one or more of historical input, historical classifications,historical user specific output, and historical scores.\n\nOriginal\n\n7\n7. (Original) The apparatus of claim 1, \nwherein displaying the user specific output using a graphical user interface of the downstream device further comprises displaying, using the graphical user interface, an interactive element.\nOriginal\n\n8\n8. (Original) The apparatus of claim 7, \nwherein the interactive element is configured to:receive user feedback regarding the user specific output;\nmodify the user specific output based on the user feedback; and\nupdate the user profile using the user feedback.\n\nOriginal\n\n9\n9. (Original) The apparatus of claim 1, \nwherein the natural language processor is further configured to adapt linguistic phrasing of the user specific output based on the attribute\n\ndata, wherein the attribute data comprises demographic preferences extracted, using the at least a processor, from the user profile.\n\nOriginal\n\n10\n10. (Original) The apparatus of claim 1, \nwherein displaying the user specific output comprises generating a graphical user interface, wherein:the graphical user interface comprises a first visual window arranged alongside a second visual window;\nthe first visual window comprises the user specific output; and\nthe second visual window is configured to present the output of a second machine learning model, wherein the second machine learning model comprises a large language model, wherein the large language model is configured to provide, as output in the second visual window, dynamic clarification as a function of the request datum and the user specific output.\n\nOriginal\n\n11\n11. (Currently Amended) A method for personalization of educational machine learning models, wherein the method comprises:receiving, using at least a processor, input data comprising one or more of a user profile and a request datum;\ngenerating, using a return generator, return output based on the request datum;\nidentifying, using a machine learning model, attribute data of the input data;\ngenerating, using a classifier, one or more classifications for the input data as a function of the attribute data associated with the input data, wherein g\nenerating\n the one of more classification using the classifier comprises:comparing, using an evaluation model, historical classifications to future activity;\n\ndetermining, using a comparison of the historical classifications to the future activity, targ\net classifications;\n\ng\nenerating\n a classification score as a function of a difference between the historical classifications and the target classifications;\n and iteratively training the classifier using the classification score;\n\nmodifying, using a natural language processor, the return output as a function of the user profile and one or more classifications assigned to the input data to generate user specific output; and Page 4 of 9 Cal\ndwell Intellectual Property Law\n\ndisplaying, using a downstream device, the user specific output.\n\nCurrently amended\n\n12\n12. (Original) The method of claim 11, \nfurther configured to generate, using the machine learning model, an alternative user specific output as a function of the input data, wherein the input data comprises activity data.\nOriginal\n\n13\n13. (Canceled)\nCanceled\n\n14\n14. (Currently Amended) The method of claim [[13]] 11, wherein the at least a processor is further configured to:compare, using the evaluation model, a historical user specific output with the future activity;\ndetermine, using a comparison of the historical user specific output with the future activity, a target user specific output;\ngenerate a user specific output score as a function of a difference between the historical user specific output and the future activity; and\niteratively train the natural language processor using the user specific output score.\n\nCurrently amended\n\n15\n15. (Original) The method of claim 14, \nwherein the evaluation model is further configured to:calculate a composite score as a function of integrating the classification score, the user specific output score;\niteratively update the composite score based on user feedback received though an interactive element; and\nprovide the composite score as training feedback for the classifier and the natural language processor.\n\nOriginal\n\n16\n16. (Original) The method of claim 11, \nfurther comprising a database communicatively connected to the at least a processor, wherein the at least a processor is configured to store, using the database, one or more of historical input, historical classifications,historical user specific output, and historical scores.\n\nOriginal\n\n17\n17. (Original) The method of claim 11, \nwherein displaying the user specific output using a graphical user interface of the downstream device further comprises displaying, using the graphical user interface, an interactive element.\nOriginal\n\n18\n18. (Original) The method of claim 17, \nwherein the interactive element is configured to:receive user feedback regarding the user specific output;\nmodify the user specific output based on the user feedback; and\n\nupdate the user profile using the user feedback.\n\nOriginal\n\n19\n19. (Original) The method of claim 11, \nwherein the natural language processor is further configured to adapt linguistic phrasing of the user specific output based on the attribute data, wherein the attribute data comprises demographic preferences extracted, using the at least a processor, from the user profile.\nOriginal\n\n20\n20. (Original) The method of claim 11, \nfurther comprising a second machine learning model,wherein the second machine learning model comprises a large language model, wherein the large language model is configured to provide, using a graphical user interface of the downstream device, dynamic clarification to the request datum.\n\nOriginal\n\nApplication Serial No.: 19/044,532 Attorney Docket: 1450-012USU1\n\nPage 2 of 9 Caldwell Intellectual Property Law\n\n200 Clarendon St.\n\n59* Floor\n\nBoston, MA 02116\n\nPage 3 of 9 Caldwell Intellectual Property Law\n\nPage 5 of 9 Caldwell Intellectual Property Law\n\nPage 6 of 9 Caldwell Intellectual Property Law"
}