{
  "id": "uspto-18760542",
  "title": "SYSTEM AND METHOD FOR COMMUNICATION DATA IDENTIFICATION AND ALERT GENERATION VIA A MACHINE LEARNING FRAMEWORK",
  "inventors": [
    "Anantharajan Srinivasarangan",
    "Dinesh Kumar Agrawal",
    "Kiran Pulla"
  ],
  "technology_class": "H04L",
  "summary": "Systems, computer program products, and methods are described herein for communication data identification and alert generation via a machine learning framework. The present disclosure includes determining a first status of an underlying service, receiving a stream of interaction data from a first user via at least one channel, classifying an interaction via a first machine learning model, generating a first notification signal via a second machine learning model, wherein the second machine learning model may be provided, as inputs, the first status of the underlying service and an interaction pattern associated with the identity, and transmitting the first notification signal via the at least one channel to a first endpoint device associated with the first user.",
  "details": "Amendments to the Claims:\nThis listing of claims will replace all prior versions and listings of claims in the application.\nPage 2 of 8\n1\n1. (Currently Amended) A system for communication data identification and alert generation via a machine learning framework, the system comprising:\na processing device;\na non-transitory storage device containing instructions when executed by the processing device, causes the processing device to perform the steps of:determining a first status of an underlying service, wherein the first status is determined based on at least one selected from the group consisting of (i) communication with at least one external interface, (ii) communication with at least one repository database;\nreceiving a stream of interaction data from a first user via at least one channel;\nclassifying an interaction via a first machine learning model, wherein classifying the interaction comprises:\nidentifying an identity of the first user based on the interaction; and determining an interaction pattern associated with the identity of the first user;\ngenerating a first notification signal via a second machine learning model,\n\nwherein the second machine learning model is provided, as inputs, the first status of the underlying service and the interaction pattern associated with the identity; [[and]] transmitting the first notification signal via the at least one channel to a first endpoint device associated with the first user;\n andreceiving, after transmitting the first notification signal, a disposition signal from the first endpoint device via the at least one channel, wherein the disposition signal comprises a disposition input.\n\nCurrently amended\n\n2\n2. (Original) The system of claim 1, \nwherein the first notification signal comprises a splash banner.\n\nReply to Office Action dated October 1, 2025 Page 3 of 8\nOriginal\n\n3\n3. (Original) The system of claim 2, \nwherein the instructions further cause the processing device to perform the steps of:displaying the splash banner on a first endpoint device associated with the first user.\n\nOriginal\n\n4\n4. (Original) The system of claim 1, \nwherein the instructions further cause the processing device to perform the steps of:generating a second notification signal via the second machine learning model;\n\nand transmitting the second notification signal to a second endpoint device associated with a second user.\nOriginal\n\n5\n5. (Original) The system of claim 1, \nwherein determining the interaction pattern associated with the identity of the first user comprises the instructions further causing the processing device to perform the steps of:collecting interaction data volume associated with the first user; and\ncomparing the interaction data volume to a predetermined interaction data baseline volume.\n\nOriginal\n\n6\n6. (Original) The system of claim 1, \nwherein the instructions further causing the processing device to perform the steps of:repeating the classifying of the interaction at a predetermined interval during the receiving of the stream of the interaction data.\n\nOriginal\n\n7\n7. (Canceled).\nCanceled\n\n8\n8. (Currently Amended) The system of claim [[7]] 1,\n wherein the disposition input comprises a request to re-route the stream of the interaction data.\n\nCurrently amended\n\n9\n9. (Original) The system of claim 1, \nwherein the identity of the first user comprises historical call frequency data and historical call duration data.\nOriginal\n\n10\n10. (Original) The system of claim 1, \nwherein the identity of the first user comprises resource transfer data associated with an account of the first user.\nOriginal\n\n11\n11. (Original) The system of claim 1, \nwherein the at least one external interface is at least one selected from a group consisting of (i) social media data feeds, and (ii) user-reported digital service disruption aggregates.\nOriginal\n\n12\n12. (Original) The system of claim 1, \nwherein the at least one repository database is at least one selected from a group consisting of (i) monitoring tool feeds, (ii) direct user inputs, and (iii) structured query reporter inputs.\nOriginal\n\n13\n13. (Original) The system of claim 1, \nwherein the at least one channel is at least one selected from a group consisting of (i) a multi-channel cognitive resource platform, (ii) a web interface, (iii) an email interface, (iv) a mobile phone application, and (v) telephone communication.\nOriginal\n\n14\n14. (Currently Amended) A computer program product for communication data identification and alert generation via a machine learning framework, the computer program product comprising a non-transitory computer-readable medium comprising code causing an apparatus to:\ndetermine a first status of an underlying service, wherein the first status is determined based on at least one selected from the group consisting of (i) communication with at least one external interface, (ii) communication with at least one repository database;\n\nreceive a stream of interaction data from a first user via at least one channel;\nclassify an interaction via a first machine learning model, wherein classifying the interaction comprises:\n\nPage 5 of 8 identifying an identity of the first user based on the interaction; and determining an interaction pattern associated with the identity of the first user;generate a first notification signal via a second machine learning model, wherein the second machine learning model is provided, as inputs, the first status of the underlying service and the interaction pattern associated with the identity; [[and]] transmit the first notification signal via the at least one channel to a first endpoint device associated with the first user;\n and\nreceive, after transmitting the first notification signal, a disposition signal from the first endpoint device via the at least one channel, wherein the disposition signal comprises a disposition input.\n\nCurrently amended\n\n15\n15. (Original) The computer program product of claim 14, \nwherein the first notification signal comprises a splash banner.\n\nOriginal\n\n16\n16. (Original) The computer program product of claim 15, \nwherein the code further causes the apparatus to:display the splash banner on a first endpoint device associated with the first user.\n\nOriginal\n\n17\n17. (Currently Amended) A method for communication data identification and alert generation via a machine learning framework, the method comprising:determining a first status of an underlying service, wherein the first status is determined based on at least one selected from the group consisting of (i) communication with at least one external interface, (ii) communication with at least one repository database;\nreceiving a stream of interaction data from a first user via at least one channel;\nclassifying an interaction via a first machine learning model, wherein classifying the interaction comprises:\nidentifying an identity of the first user based on the interaction; and\n\nPage 6 of 8 determining an interaction pattern associated with the identity of the first user;generating a first notification signal via a second machine learning model,\nwherein the second machine learning model is provided, as inputs, the first status of the underlying service and the interaction pattern associated with the identity; [[and]] transmitting the first notification signal via the at least one channel to a first endpoint device associated with the first user;\n andreceiving, after transmitting the first notification signal, a disposition signal from the first endpoint device via the at least one channel, wherein the disposition signal comprises a disposition input.\n\nCurrently amended\n\n18\n18. (Original) The method of claim 17, \nwherein the first notification signal comprises a splash banner.\nOriginal\n\n19\n19. (Original) The method of claim 18, \nfurther comprising:displaying the splash banner on a first endpoint device associated with the first user.\n\nOriginal\n\n20\n20. (Original) The method of claim 17, \nfurther comprising:generating a second notification signal via the second machine learning model;\n\nand transmitting the second notification signal to a second endpoint device associated with a second user.\nOriginal\n\n21\n21. (New) The computer program product of claim 14, \nwherein the code further causes the apparatus to:generate a second notification signal via the second machine learning model; and\ntransmit the second notification signal to a second endpoint device associated with a second user.\n\nNew\n\nAppl. No.: 18/760,542\n\nAmdt. Dated: December 29, 2025\n\nReply to Office Action dated October 1, 2025\n\nPage 4 of 8"
}